{
  "iik": {
    "ad": "İİK (2004 s.K.)",
    "madde": 398,
    "son_senkron": "2026-07-15",
    "hash": "7E2866514CAED2D5"
  },
  "is": {
    "ad": "İş K. (4857 s.K.)",
    "madde": 119,
    "son_senkron": "2026-07-15",
    "hash": "3F65C4C779A97419"
  },
  "aatuhk": {
    "ad": "AATUHK (6183 s.K.)",
    "madde": 136,
    "son_senkron": "2026-07-15",
    "hash": "2EC5294DAE7A2695"
  },
  "gvk": {
    "ad": "GVK (193 s.K.)",
    "madde": 219,
    "son_senkron": "2026-07-15",
    "hash": "D89F5593848E83B8"
  },
  "ttk": {
    "ad": "TTK (6102 s.K.)",
    "madde": 1530,
    "son_senkron": "2026-07-15",
    "hash": "0A4A2CC49818DB16"
  },
  "gumruk": {
    "ad": "Gümrük K. (4458 s.K.)",
    "madde": 253,
    "son_senkron": "2026-07-15",
    "hash": "21FAA7B44F5CEA69"
  },
  "kdv": {
    "ad": "KDVK (3065 s.K.)",
    "madde": 111,
    "son_senkron": "2026-07-15",
    "hash": "7352F6A5F9CD6104"
  },
  "kvk": {
    "ad": "KVK (5520 s.K.)",
    "madde": 71,
    "son_senkron": "2026-07-15",
    "hash": "B5B8A4AE9CF4A70C"
  },
  "vuk": {
    "ad": "VUK (213 s.K.)",
    "madde": 452,
    "son_senkron": "2026-07-15",
    "hash": "237DAFA5A7F7C60A"
  }
}