{
    "kaynak":  "GİB — Faiz ve Gayrimaddi Hak Bedelleri Üzerinden Kaynak Devlette Alınacak Vergi Oranları (yürürlükteki ÇVÖA\u0027lar)",
    "not":  "Oranlar gayrimaddi hak (royalti/telif) icin kaynak devlette (Türkiye) alinacak stopaj UST SINIRIDIR. Gosterilen deger GENEL/tipik royalti (patent, marka, lisans, yazilim telifi) icindir; ekipman/film gibi ozel kullanimlarda karttaki nota bak. Kesin oran ve istisnalar icin anlasma metni esastir.",
    "ulkeler":  {
                    "A.B.D":  {
                                  "r":  10,
                                  "f":  10,
                                  "n":  "Sınai/ticari/bilimsel ekipman kullanımında %5; patent/marka/telif %10"
                              },
                    "ARJANTİN":  {
                                     "r":  10,
                                     "f":  12,
                                     "n":  "Patent/marka/diğer %10; edebi-sanatsal telif %5; haber ajansı %3"
                                 },
                    "ARNAVUTLUK":  {
                                       "r":  10,
                                       "f":  10
                                   },
                    "AVUSTRALYA":  {
                                       "r":  10,
                                       "f":  10
                                   },
                    "AVUSTURYA":  {
                                      "r":  10,
                                      "f":  15
                                  },
                    "AZERBAYCAN":  {
                                       "r":  10,
                                       "f":  10
                                   },
                    "B.A.E":  {
                                  "r":  10,
                                  "f":  10
                              },
                    "BAHREYN":  {
                                    "r":  10,
                                    "f":  10
                                },
                    "BANGLADEŞ":  {
                                      "r":  10,
                                      "f":  10
                                  },
                    "BELÇİKA":  {
                                    "r":  10,
                                    "f":  15
                                },
                    "BEYAZ RUSYA":  {
                                        "r":  10,
                                        "f":  10
                                    },
                    "BOSNA HERSEK":  {
                                         "r":  10,
                                         "f":  10
                                     },
                    "BREZİLYA":  {
                                     "r":  10,
                                     "f":  15,
                                     "n":  "Ticari marka %15; diğer gayrimaddi hak %10"
                                 },
                    "BULGARİSTAN":  {
                                        "r":  10,
                                        "f":  10
                                    },
                    "CEZAYİR":  {
                                    "r":  10,
                                    "f":  10
                                },
                    "Ç.H.C":  {
                                  "r":  10,
                                  "f":  10
                              },
                    "ÇAD":  {
                                "r":  10,
                                "f":  10
                            },
                    "ÇEK CUM":  {
                                    "r":  10,
                                    "f":  10
                                },
                    "DANİMARKA":  {
                                      "r":  10,
                                      "f":  15
                                  },
                    "ENDONEZYA":  {
                                      "r":  10,
                                      "f":  10
                                  },
                    "ESTONYA":  {
                                    "r":  10,
                                    "f":  10,
                                    "n":  "Sınai/ticari/bilimsel ekipman kullanımında %5; diğer %10"
                                },
                    "ETİYOPYA":  {
                                     "r":  10,
                                     "f":  10
                                 },
                    "FAS":  {
                                "r":  10,
                                "f":  10
                            },
                    "FİLİPİNLER":  {
                                       "r":  10,
                                       "f":  10,
                                       "n":  "Film/radyo-TV bantları %15; edebi-sanatsal telif %10"
                                   },
                    "FİNLANDİYA":  {
                                       "r":  10,
                                       "f":  15
                                   },
                    "FRANSA":  {
                                   "r":  10,
                                   "f":  15
                               },
                    "GAMBİYA":  {
                                    "r":  10,
                                    "f":  10
                                },
                    "GÜNEY AFRİKA C":  {
                                           "r":  10,
                                           "f":  10
                                       },
                    "GÜNEY KORE":  {
                                       "r":  10,
                                       "f":  10
                                   },
                    "GÜRCİSTAN":  {
                                      "r":  10,
                                      "f":  10
                                  },
                    "HIRVATİSTAN":  {
                                        "r":  10,
                                        "f":  10
                                    },
                    "HİNDİSTAN":  {
                                      "r":  15,
                                      "f":  10,
                                      "n":  "Genel %15; finans kurumu faizli borçta bağlı özel durumlar"
                                  },
                    "HOLLANDA":  {
                                     "r":  10,
                                     "f":  10
                                 },
                    "İNGİLTERE":  {
                                      "r":  10,
                                      "f":  15
                                  },
                    "İRAN":  {
                                 "r":  10,
                                 "f":  10
                             },
                    "İRLANDA":  {
                                    "r":  10,
                                    "f":  10,
                                    "n":  "Genel gayrimaddi hak %10 (parser faiz oranını karıştırmıştı — düzeltildi)"
                                },
                    "İSRAİL":  {
                                   "r":  10,
                                   "f":  10
                               },
                    "İSVEÇ":  {
                                  "r":  10,
                                  "f":  15
                              },
                    "İSVİÇRE":  {
                                    "r":  10,
                                    "f":  5
                                },
                    "İTALYA":  {
                                   "r":  10,
                                   "f":  15
                               },
                    "JAPONYA":  {
                                    "r":  10,
                                    "f":  10
                                },
                    "KAMBOÇYA":  {
                                     "r":  10,
                                     "f":  10
                                 },
                    "KANADA":  {
                                   "r":  10,
                                   "f":  15
                               },
                    "KARADAĞ":  {
                                    "r":  10,
                                    "f":  10
                                },
                    "KATAR":  {
                                  "r":  10,
                                  "f":  10
                              },
                    "KAZAKİSTAN":  {
                                       "r":  10,
                                       "f":  10
                                   },
                    "KIRGIZİSTAN":  {
                                        "r":  10,
                                        "f":  10
                                    },
                    "KKTC":  {
                                 "r":  10,
                                 "f":  10
                             },
                    "KOSOVA":  {
                                   "r":  10,
                                   "f":  10
                               },
                    "KUVEYT":  {
                                   "r":  10,
                                   "f":  10
                               },
                    "LETONYA":  {
                                    "r":  10,
                                    "f":  10,
                                    "n":  "Sınai/ticari/bilimsel ekipman kullanımında %5; diğer %10"
                                },
                    "LİTVANYA":  {
                                     "r":  10,
                                     "f":  10,
                                     "n":  "Sınai/ticari/bilimsel ekipman kullanımında %5; diğer %10"
                                 },
                    "LÜBNAN":  {
                                   "r":  10,
                                   "f":  10
                               },
                    "LÜKSEMBURG":  {
                                       "r":  10,
                                       "f":  10
                                   },
                    "MACARİSTAN":  {
                                       "r":  10,
                                       "f":  10
                                   },
                    "MAKEDONYA":  {
                                      "r":  10,
                                      "f":  10
                                  },
                    "MALEZYA":  {
                                    "r":  10,
                                    "f":  15
                                },
                    "MALTA":  {
                                  "r":  10,
                                  "f":  10
                              },
                    "MEKSİKA":  {
                                    "r":  10,
                                    "f":  10
                                },
                    "MISIR":  {
                                  "r":  10,
                                  "f":  10
                              },
                    "MOĞOLİSTAN":  {
                                       "r":  10,
                                       "f":  10
                                   },
                    "MOLDOVA":  {
                                    "r":  10,
                                    "f":  10
                                },
                    "NORVEÇ":  {
                                   "r":  10,
                                   "f":  15
                               },
                    "ÖZBEKİSTAN":  {
                                       "r":  10,
                                       "f":  10
                                   },
                    "PAKİSTAN":  {
                                     "r":  10,
                                     "f":  10
                                 },
                    "POLONYA":  {
                                    "r":  10,
                                    "f":  10
                                },
                    "PORTEKİZ":  {
                                     "r":  10,
                                     "f":  10
                                 },
                    "ROMANYA":  {
                                    "r":  10,
                                    "f":  10
                                },
                    "RUANDA":  {
                                   "r":  10,
                                   "f":  10
                               },
                    "RUSYA":  {
                                  "r":  10,
                                  "f":  10
                              },
                    "SIRBİSTAN":  {
                                      "r":  10,
                                      "f":  10
                                  },
                    "SİERRA LEONE":  {
                                         "r":  10,
                                         "f":  10
                                     },
                    "SLOVAKYA":  {
                                     "r":  10,
                                     "f":  10
                                 },
                    "SLOVENYA":  {
                                     "r":  10,
                                     "f":  10
                                 },
                    "SRİ LANKA":  {
                                      "r":  10,
                                      "f":  10
                                  },
                    "SUDAN":  {
                                  "r":  10,
                                  "f":  10
                              },
                    "SURİYE":  {
                                   "r":  15,
                                   "f":  10,
                                   "n":  "Patent/marka/desen/formül/sınai-ticari tecrübe %15"
                               },
                    "TACİKİSTAN":  {
                                       "r":  10,
                                       "f":  10
                                   },
                    "TAYLAND":  {
                                    "r":  15,
                                    "f":  10,
                                    "n":  "Genel %15"
                                },
                    "TUNUS":  {
                                  "r":  10,
                                  "f":  10
                              },
                    "TÜRKMENİSTAN":  {
                                         "r":  10,
                                         "f":  10
                                     },
                    "UKRAYNA":  {
                                    "r":  10,
                                    "f":  10
                                },
                    "UMMAN":  {
                                  "r":  10,
                                  "f":  10
                              },
                    "ÜRDÜN":  {
                                  "r":  12,
                                  "f":  10,
                                  "n":  "Genel %12"
                              },
                    "VENEZUELA":  {
                                      "r":  10,
                                      "f":  10
                                  },
                    "VİETNAM":  {
                                    "r":  10,
                                    "f":  10
                                },
                    "YEMEN":  {
                                  "r":  10,
                                  "f":  10
                              },
                    "YENİ ZELANDA":  {
                                         "r":  10,
                                         "f":  10
                                     },
                    "YUNANİSTAN":  {
                                       "r":  10,
                                       "f":  12
                                   },
                    "İSPANYA":  {
                                    "r":  10,
                                    "f":  10,
                                    "n":  "Genel gayrimaddi hak %10"
                                },
                    "ALMANYA":  {
                                    "r":  10,
                                    "f":  10,
                                    "n":  "Yürürlükteki (yeni) anlaşma: gayrimaddi hak %10"
                                },
                    "SİNGAPUR":  {
                                     "r":  10,
                                     "f":  10,
                                     "n":  "Gayrimaddi hak %10; faiz finans kurumunda %7,5"
                                 }
                }
}
