{
    "tarih":  "30.09.2025",
    "kaynak":  "https://www.resmigazete.gov.tr/30.09.2025",
    "toplam":  1,
    "kategoriler":  {
                        "Gözetim / Damping / Korunma":  [

                                                        ],
                        "Ürün Güvenliği / Denetim":  [

                                                     ],
                        "Gümrük / İthalat-İhracat":  [

                                                     ],
                        "Kambiyo / Finans":  [

                                             ],
                        "Vergi":  [

                                  ],
                        "Teşvik / Destek":  [

                                            ],
                        "Çalışma / SGK":  [

                                          ]
                    },
    "kategorisiz":  [
                        {
                            "baslik":  "İstanbul Üniversitesi Küresel Siyaset ve Yönetim Uygulama ve Araştırma Merkezi Yönetmeliği",
                            "url":  "https://www.resmigazete.gov.tr/eskiler/2025/09/20250930-2.htm"
                        }
                    ]
}
