{
    "tarih":  "29.06.2026",
    "kaynak":  "https://www.resmigazete.gov.tr/29.06.2026",
    "toplam":  1,
    "kategoriler":  {
                        "Gözetim / Damping / Korunma":  [

                                                        ],
                        "Ürün Güvenliği / Denetim":  [

                                                     ],
                        "Gümrük / İthalat-İhracat":  [

                                                     ],
                        "Kambiyo / Finans":  [

                                             ],
                        "Vergi":  [

                                  ],
                        "Teşvik / Destek":  [

                                            ],
                        "Çalışma / SGK":  [

                                          ]
                    },
    "kategorisiz":  [
                        {
                            "baslik":  "KTO-Karatay Üniversitesi Uygulamalı Bilimler Yüksekokulu Pilotaj Bölümü Eğitim-Öğretim ve Sınav Yönetmeliği",
                            "url":  "https://www.resmigazete.gov.tr/eskiler/2026/06/20260629-1.htm"
                        }
                    ]
}
