{
    "tarih":  "22.10.2025",
    "kaynak":  "https://www.resmigazete.gov.tr/22.10.2025",
    "toplam":  2,
    "kategoriler":  {
                        "Gözetim / Damping / Korunma":  [

                                                        ],
                        "Ürün Güvenliği / Denetim":  [

                                                     ],
                        "Gümrük / İthalat-İhracat":  [

                                                     ],
                        "Kambiyo / Finans":  [

                                             ],
                        "Vergi":  [

                                  ],
                        "Teşvik / Destek":  [

                                            ],
                        "Çalışma / SGK":  [

                                          ]
                    },
    "kategorisiz":  [
                        {
                            "baslik":  "İstanbul Aydın Üniversitesi Eczacılık Fakültesi Eğitim-Öğretim ve Sınav Yönetmeliğinde Değişiklik Yapılmasına Dair Yönetmelik",
                            "url":  "https://www.resmigazete.gov.tr/eskiler/2025/10/20251022-1.htm"
                        },
                        {
                            "baslik":  "Yeditepe Üniversitesi İhale Yönetmeliğinde Değişiklik Yapılmasına Dair Yönetmelik",
                            "url":  "https://www.resmigazete.gov.tr/eskiler/2025/10/20251022-2.htm"
                        }
                    ]
}
