{
    "tarih":  "24.05.2026",
    "kaynak":  "https://www.resmigazete.gov.tr/24.05.2026",
    "toplam":  6,
    "kategoriler":  {
                        "Gözetim / Damping / Korunma":  [
                                                            {
                                                                "baslik":  "İthalatta Haksız Rekabetin Önlenmesine İlişkin Tebliğ (No: 2026/16)",
                                                                "url":  "https://www.resmigazete.gov.tr/eskiler/2026/05/20260524-4.htm"
                                                            },
                                                            {
                                                                "baslik":  "İthalatta Haksız Rekabetin Önlenmesine İlişkin Tebliğ (No: 2026/19)",
                                                                "url":  "https://www.resmigazete.gov.tr/eskiler/2026/05/20260524-5.htm"
                                                            },
                                                            {
                                                                "baslik":  "İthalatta Haksız Rekabetin Önlenmesine İlişkin Tebliğ (No: 2026/20)",
                                                                "url":  "https://www.resmigazete.gov.tr/eskiler/2026/05/20260524-6.htm"
                                                            }
                                                        ],
                        "Ürün Güvenliği / Denetim":  [

                                                     ],
                        "Gümrük / İthalat-İhracat":  [

                                                     ],
                        "Kambiyo / Finans":  [

                                             ],
                        "Vergi":  [
                                      {
                                          "baslik":  "Kurumlar Vergisi Genel Tebliği (Seri No: 1)’nde Değişiklik Yapılmasına Dair Tebliğ (Seri No: 25)",
                                          "url":  "https://www.resmigazete.gov.tr/eskiler/2026/05/20260524-3.htm"
                                      }
                                  ],
                        "Teşvik / Destek":  [

                                            ],
                        "Çalışma / SGK":  [

                                          ]
                    },
    "kategorisiz":  [
                        {
                            "baslik":  "İstanbul Beykent Üniversitesi Türkçe Öğretimi Uygulama ve Araştırma Merkezi Yönetmeliğinde Değişiklik Yapılmasına Dair Yönetmelik",
                            "url":  "https://www.resmigazete.gov.tr/eskiler/2026/05/20260524-1.htm"
                        },
                        {
                            "baslik":  "Uşak Üniversitesi Lisansüstü Eğitim ve Öğretim Yönetmeliği",
                            "url":  "https://www.resmigazete.gov.tr/eskiler/2026/05/20260524-2.htm"
                        }
                    ]
}
