{
    "tarih":  "15.04.2026",
    "kaynak":  "https://www.resmigazete.gov.tr/15.04.2026",
    "toplam":  4,
    "kategoriler":  {
                        "Gözetim / Damping / Korunma":  [
                                                            {
                                                                "baslik":  "İthalatta Haksız Rekabetin Önlenmesine İlişkin Tebliğ (Tebliğ No: 2025/31)’de Değişiklik Yapılmasına Dair Tebliğ",
                                                                "url":  "https://www.resmigazete.gov.tr/eskiler/2026/04/20260415-4.htm"
                                                            }
                                                        ],
                        "Ürün Güvenliği / Denetim":  [

                                                     ],
                        "Gümrük / İthalat-İhracat":  [

                                                     ],
                        "Kambiyo / Finans":  [

                                             ],
                        "Vergi":  [

                                  ],
                        "Teşvik / Destek":  [

                                            ],
                        "Çalışma / SGK":  [

                                          ]
                    },
    "kategorisiz":  [
                        {
                            "baslik":  "Hatay Mustafa Kemal Üniversitesi Veteriner Sağlık Uygulama ve Araştırma Merkezi Yönetmeliğinde Değişiklik Yapılmasına Dair Yönetmelik",
                            "url":  "https://www.resmigazete.gov.tr/eskiler/2026/04/20260415-1.htm"
                        },
                        {
                            "baslik":  "Tarsus Üniversitesi Lisansüstü Eğitim-Öğretim ve Sınav Yönetmeliğinde Değişiklik Yapılmasına Dair Yönetmelik",
                            "url":  "https://www.resmigazete.gov.tr/eskiler/2026/04/20260415-2.htm"
                        },
                        {
                            "baslik":  "Elektrikli Skuterlerin Üretimindeki Yerlilik Esasları Hakkında Tebliğ (SGM-2026/5)",
                            "url":  "https://www.resmigazete.gov.tr/eskiler/2026/04/20260415-3.htm"
                        }
                    ]
}
